ShidaiXingxingHuijideYinicangbanRensheng/README.md
ShidaiXingxingHuijideYinicangbanRensheng/__init__.py
ShidaiXingxingHuijideYinicangbanRensheng/__main__.py
ShidaiXingxingHuijideYinicangbanRensheng/file.pdf
ShidaiXingxingHuijideYinicangbanRensheng/index.html
shidai_xingxing_huijide_yinicangban_rensheng-2022.10.14.0.dist-info/METADATA
shidai_xingxing_huijide_yinicangban_rensheng-2022.10.14.0.dist-info/WHEEL
shidai_xingxing_huijide_yinicangban_rensheng-2022.10.14.0.dist-info/entry_points.txt
shidai_xingxing_huijide_yinicangban_rensheng-2022.10.14.0.dist-info/top_level.txt
shidai_xingxing_huijide_yinicangban_rensheng-2022.10.14.0.dist-info/RECORD
